[
  {
    "step": 1,
    "train_nll": 10.9323,
    "page_nll": 10.8714,
    "page_ppl": 52649.2
  },
  {
    "step": 250,
    "train_nll": 3.8754,
    "page_nll": 4.0332,
    "page_ppl": 56.4
  },
  {
    "step": 500,
    "train_nll": 1.9195,
    "page_nll": 2.0405,
    "page_ppl": 7.7
  },
  {
    "step": 750,
    "train_nll": 0.7296,
    "page_nll": 0.7782,
    "page_ppl": 2.2
  },
  {
    "step": 1000,
    "train_nll": 0.2964,
    "page_nll": 0.3128,
    "page_ppl": 1.4
  },
  {
    "step": 1250,
    "train_nll": 0.2352,
    "page_nll": 0.2067,
    "page_ppl": 1.2
  },
  {
    "step": 1500,
    "train_nll": 0.1867,
    "page_nll": 0.1616,
    "page_ppl": 1.2
  }
]